form_creator/__init__.py
form_creator/admin.py
form_creator/apps.py
form_creator/decorators.py
form_creator/exporters.py
form_creator/form_fields.py
form_creator/forms.py
form_creator/managers.py
form_creator/models.py
form_creator/question_form_fields.py
form_creator/urls.py
form_creator/views.py
form_creator/migrations/0001_initial.py
form_creator/migrations/__init__.py
form_creator/static/form_creator/js/additional_questions.js
form_creator/templates/base.html
form_creator/templates/admin/form_creator/form/change_form.html
form_creator/templates/form_creator/_form_questions_table.html
form_creator/templates/form_creator/form_create.html
form_creator/templates/form_creator/form_delete.html
form_creator/templates/form_creator/form_detail.html
form_creator/templates/form_creator/form_edit.html
form_creator/templates/form_creator/form_list.html
form_creator/templates/form_creator/form_questions_edit.html
form_creator/templates/form_creator/form_response.html
form_creator/templatetags/__init__.py
form_creator/templatetags/form_creator_tags.py
form_creator/tests/__init__.py
form_creator/tests/test_admin.py
form_creator/tests/test_decorators.py
form_creator/tests/test_exporters.py
form_creator/tests/test_form_fields.py
form_creator/tests/test_forms.py
form_creator/tests/test_manager.py
form_creator/tests/test_models.py
form_creator/tests/test_question_form_fields.py
form_creator/tests/test_templatetags_form_creator_tags.py
form_creator/tests/test_views.py
django_form_creator-1.0.0.dist-info/LICENSE
django_form_creator-1.0.0.dist-info/METADATA
django_form_creator-1.0.0.dist-info/WHEEL
django_form_creator-1.0.0.dist-info/top_level.txt
django_form_creator-1.0.0.dist-info/RECORD
