Metadata-Version: 2.1
Name: django-form-creator
Version: 1.0.0
Summary: A Django application that lets users dynamically create forms.
Home-page: https://github.com/Salaah01/django-form-creator
Author: Salaah Amin
License: MIT
Platform: UNKNOWN
Classifier: Intended Audience :: Developers
Classifier: Operating System :: OS Independent
Classifier: Programming Language :: Python
Classifier: Programming Language :: Python :: 3
Classifier: Programming Language :: Python :: 3 :: Only
Classifier: Programming Language :: Python :: 3.8
Classifier: Programming Language :: Python :: 3.9
Classifier: Topic :: Software Development :: Libraries :: Python Modules
Requires-Python: >=3.6
Requires-Dist: django (>=3.2)
